quicly_redis/__init__.py
quicly_redis/quicly_redis.py
quicly_redis-0.0.1.dist-info/METADATA
quicly_redis-0.0.1.dist-info/WHEEL
quicly_redis-0.0.1.dist-info/top_level.txt
quicly_redis-0.0.1.dist-info/RECORD
